MANIFEST.in
README.txt
anthill.customexport-configure.zcml
setup.cfg
setup.py
anthill/__init__.py
anthill.customexport.egg-info/PKG-INFO
anthill.customexport.egg-info/SOURCES.txt
anthill.customexport.egg-info/dependency_links.txt
anthill.customexport.egg-info/entry_points.txt
anthill.customexport.egg-info/namespace_packages.txt
anthill.customexport.egg-info/not-zip-safe
anthill.customexport.egg-info/requires.txt
anthill.customexport.egg-info/top_level.txt
anthill/customexport/__init__.py
anthill/customexport/configure.zcml
anthill/customexport/exportfs.pt
anthill/customexport/interfaces.py
anthill/customexport/patch.py
anthill/customexport/tests.py
anthill/customexport/zope2.py
docs/HISTORY.txt