Metadata-Version: 1.0
Name: anthill.customexport
Version: 0.3
Summary: Makes it possible to export custom folder contents (from portal_skins/custom and portal_view_customizations) to filesystem
Home-page: UNKNOWN
Author: Simon Pamies
Author-email: s.pamies@banality.de
License: GPL
Keywords: zope patch customfolder skinning theme skin plone
Platform: UNKNOWN
Classifier: Programming Language :: Python
Classifier: Topic :: Software Development :: Libraries :: Python Modules
